README.txt
setup.py
PyToggl/PyToggl.py
PyToggl/__init__.py
PyToggl.egg-info/PKG-INFO
PyToggl.egg-info/SOURCES.txt
PyToggl.egg-info/dependency_links.txt
PyToggl.egg-info/requires.txt
PyToggl.egg-info/top_level.txt