Metadata-Version: 1.1
Name: PyToggl
Version: 0.2.5
Summary: The Definitive Python Library For The Toggl API
Home-page: http://github.com/smeggingsmegger/PyToggl
Author: Scott Blevins
Author-email: sblevins@gmail.com
License: MIT
Keywords: Toggl,Time,Tracking,Library,API
Platform: OS Independent
Classifier: Development Status :: 3 - Alpha
Classifier: License :: OSI Approved :: MIT License
Classifier: Operating System :: OS Independent
Classifier: Programming Language :: Python :: 2.7
Classifier: Intended Audience :: Developers
Classifier: Topic :: Software Development :: Libraries :: Python Modules
